./.gitignore
./__init__.py
./pyproject.toml
./ibm_watsonx_orchestrate_mcp_server/__init__.py
./ibm_watsonx_orchestrate_mcp_server/server.py
./ibm_watsonx_orchestrate_mcp_server/src/__init__.py
./ibm_watsonx_orchestrate_mcp_server/src/version_checker.py
./ibm_watsonx_orchestrate_mcp_server/src/agents/mcp_tools.py
./ibm_watsonx_orchestrate_mcp_server/src/agents/types.py
./ibm_watsonx_orchestrate_mcp_server/src/channels/mcp_tools.py
./ibm_watsonx_orchestrate_mcp_server/src/channels/types.py
./ibm_watsonx_orchestrate_mcp_server/src/connections/helpers.py
./ibm_watsonx_orchestrate_mcp_server/src/connections/mcp_tools.py
./ibm_watsonx_orchestrate_mcp_server/src/connections/types.py
./ibm_watsonx_orchestrate_mcp_server/src/knowledge_bases/mcp_tools.py
./ibm_watsonx_orchestrate_mcp_server/src/models/mcp_tools.py
./ibm_watsonx_orchestrate_mcp_server/src/models/types.py
./ibm_watsonx_orchestrate_mcp_server/src/phone/mcp_tools.py
./ibm_watsonx_orchestrate_mcp_server/src/phone/types.py
./ibm_watsonx_orchestrate_mcp_server/src/toolkits/mcp_tools.py
./ibm_watsonx_orchestrate_mcp_server/src/toolkits/types.py
./ibm_watsonx_orchestrate_mcp_server/src/tools/mcp_tools.py
./ibm_watsonx_orchestrate_mcp_server/src/voice_configurations/mcp_tools.py
./ibm_watsonx_orchestrate_mcp_server/utils/common.py
./ibm_watsonx_orchestrate_mcp_server/utils/config/__init__.py
./ibm_watsonx_orchestrate_mcp_server/utils/config/config.py
./ibm_watsonx_orchestrate_mcp_server/utils/config/types.py
./ibm_watsonx_orchestrate_mcp_server/utils/files/files.py
./ibm_watsonx_orchestrate_mcp_server/utils/logging/__init__.py
./ibm_watsonx_orchestrate_mcp_server/utils/logging/log_config.yaml
./ibm_watsonx_orchestrate_mcp_server/utils/logging/logger.py
ibm_watsonx_orchestrate_mcp_server-2.3.0.dist-info/METADATA
ibm_watsonx_orchestrate_mcp_server-2.3.0.dist-info/WHEEL
ibm_watsonx_orchestrate_mcp_server-2.3.0.dist-info/entry_points.txt
ibm_watsonx_orchestrate_mcp_server-2.3.0.dist-info/RECORD
