Metadata-Version: 2.4
Name: ibm-watsonx-orchestrate-mcp-server
Version: 2.3.0
Summary: IBM watsonx Orchestrate ADK MCP Server
Author-email: IBM <support@ibm.com>
License: MIT License
Requires-Python: <3.14,>=3.11
Requires-Dist: authlib>=1.6.3
Requires-Dist: fastmcp~=2.10
Requires-Dist: ibm-watsonx-orchestrate>=1.16.0
Requires-Dist: pyyaml<7.0.0,>=6.0.2
Requires-Dist: typing-extensions>=4.4.0
